SamAuthenticator
