Metadata-Version: 1.0
Name: samauth
Version: 1.0.6
Summary: A simple Google Authenticator replacement
Home-page: https://git.afach.de/samerafach/SamAuthenticator
Author: Samer Afach
Author-email: samer@afach.de
License: UNKNOWN
Platform: UNKNOWN
